{
"skeleton": {
	"hash": "FABLvUS1PP0",
	"spine": "4.1.21",
	"x": -1180,
	"y": -3,
	"width": 2361,
	"height": 403,
	"images": "./images/",
	"audio": "C:/Users/juhee/Desktop/ck_work/3-2/퓨처리티/리소스/스트리트/cyber_implant"
},
"bones": [
	{ "name": "root" }
],
"slots": [
	{ "name": "cyber_implant_shadow", "bone": "root", "attachment": "cyber_implant_shadow" },
	{ "name": "cyber_implant", "bone": "root", "attachment": "cyber_implant" }
],
"skins": [
	{
		"name": "default",
		"attachments": {
			"cyber_implant": {
				"cyber_implant": { "x": 0.5, "y": 198.5, "width": 2361, "height": 403 }
			},
			"cyber_implant_shadow": {
				"cyber_implant_shadow": { "x": 0.5, "y": 198.5, "width": 2361, "height": 403 }
			}
		}
	}
],
"animations": {
	"cyber_implant": {
		"slots": {
			"cyber_implant": {
				"rgba": [
					{
						"color": "ffffffff",
						"curve": [ 0.111, 1, 0.222, 1, 0.111, 1, 0.222, 1, 0.111, 1, 0.222, 1, 0.111, 1, 0.222, 0.62 ]
					},
					{
						"time": 0.3333,
						"color": "ffffff9d",
						"curve": [ 0.356, 1, 0.378, 1, 0.356, 1, 0.378, 1, 0.356, 1, 0.378, 1, 0.356, 0.62, 0.378, 0.98 ]
					},
					{
						"time": 0.4,
						"color": "ffffffff",
						"curve": [ 0.423, 1, 0.445, 1, 0.423, 1, 0.445, 1, 0.423, 1, 0.445, 1, 0.423, 1.02, 0.445, 0 ]
					},
					{
						"time": 0.4667,
						"color": "ffffff00",
						"curve": [ 0.534, 1, 0.511, 1, 0.534, 1, 0.511, 1, 0.534, 1, 0.511, 1, 0.534, 0.01, 0.511, 0.98 ]
					},
					{ "time": 0.5333, "color": "ffffffff" },
					{
						"time": 0.6,
						"color": "ffffff00",
						"curve": [ 0.667, 1, 0.644, 1, 0.667, 1, 0.644, 1, 0.667, 1, 0.644, 1, 0.667, 0.01, 0.644, 1 ]
					},
					{
						"time": 0.6667,
						"color": "ffffffff",
						"curve": [ 0.778, 1, 0.889, 1, 0.778, 1, 0.889, 1, 0.778, 1, 0.889, 1, 0.778, 1, 0.889, 0.62 ]
					},
					{
						"time": 1,
						"color": "ffffff9d",
						"curve": [ 1.111, 1, 1.222, 1, 1.111, 1, 1.222, 1, 1.111, 1, 1.222, 1, 1.111, 0.62, 1.222, 1 ]
					},
					{
						"time": 1.3333,
						"color": "ffffffff",
						"curve": [ 1.444, 1, 1.556, 1, 1.444, 1, 1.556, 1, 1.444, 1, 1.556, 1, 1.444, 1, 1.556, 0.49 ]
					},
					{
						"time": 1.6667,
						"color": "ffffff9d",
						"curve": [ 1.778, 1, 1.889, 1, 1.778, 1, 1.889, 1, 1.778, 1, 1.889, 1, 1.778, 0.74, 1.889, 1 ]
					},
					{
						"time": 2,
						"color": "ffffffff",
						"curve": [ 2.111, 1, 2.222, 1, 2.111, 1, 2.222, 1, 2.111, 1, 2.222, 1, 2.111, 1, 2.222, 0.62 ]
					},
					{
						"time": 2.3333,
						"color": "ffffff9d",
						"curve": [ 2.444, 1, 2.556, 1, 2.444, 1, 2.556, 1, 2.444, 1, 2.556, 1, 2.444, 0.62, 2.556, 1 ]
					},
					{
						"time": 2.6667,
						"color": "ffffffff",
						"curve": [ 2.778, 1, 2.889, 1, 2.778, 1, 2.889, 1, 2.778, 1, 2.889, 1, 2.778, 1, 2.889, 0.62 ]
					},
					{
						"time": 3,
						"color": "ffffff9d",
						"curve": [ 3.111, 1, 3.222, 1, 3.111, 1, 3.222, 1, 3.111, 1, 3.222, 1, 3.111, 0.62, 3.222, 1 ]
					},
					{ "time": 3.3333, "color": "ffffffff" }
				]
			}
		}
	}
}
}