<?xml version="1.0" encoding="UTF-8"?>
<objects serializationModel="Studio.02.02.00">
	<object class="AudioFile" id="{21074b7e-f7e9-4f92-b4d8-35e0914de3fe}">
		<property name="assetPath">
			<value>Player/Voices/Hit, damage_06 (6), damage_06 (6).wav</value>
		</property>
		<property name="frequencyInKHz">
			<value>44.0999985</value>
		</property>
		<property name="channelCount">
			<value>2</value>
		</property>
		<property name="length">
			<value>0.63904761904761909</value>
		</property>
		<relationship name="masterAssetFolder">
			<destination>{45d3d336-8f9a-4b46-84c5-50850a5027c3}</destination>
		</relationship>
	</object>
</objects>
